justrunalready/__init__.py
justrunalready/config.py
justrunalready/models.py
justrunalready/py.typed
justrunalready/cli/__init__.py
justrunalready/cli/main.py
justrunalready/cli/utils.py
justrunalready/cli/commands/__init__.py
justrunalready/cli/commands/bundle.py
justrunalready/cli/commands/doctor.py
justrunalready/cli/commands/info.py
justrunalready/cli/commands/tree.py
justrunalready/cli/commands/verify.py
justrunalready/data/__init__.py
justrunalready/data/appimage_excludelist.txt
justrunalready/inspectors/__init__.py
justrunalready/inspectors/base.py
justrunalready/inspectors/linux.py
justrunalready/inspectors/loader.py
justrunalready/inspectors/macos.py
justrunalready/inspectors/windows.py
justrunalready/patchers/linux.py
justrunalready/patchers/macos.py
justrunalready/platforms/__init__.py
justrunalready/platforms/base.py
justrunalready/platforms/linux.py
justrunalready/platforms/loader.py
justrunalready/platforms/macos.py
justrunalready/platforms/windows.py
justrunalready/utils/__init__.py
justrunalready/utils/resolve.py
justrunalready/wrappers/__init__.py
justrunalready/wrappers/appimage.py
justrunalready/wrappers/dmg.py
justrunalready/wrappers/loader.py
justrunalready/wrappers/zip.py
justrunalready-0.1.13.dist-info/METADATA
justrunalready-0.1.13.dist-info/WHEEL
justrunalready-0.1.13.dist-info/entry_points.txt
justrunalready-0.1.13.dist-info/RECORD
