Metadata-Version: 2.4
Name: justrunalready
Version: 0.1.13
Summary: Win/Linux/Mac bundler helper.
Author-email: Tyler Kennedy <tk@tkte.ch>
Requires-Python: >=3.11
Requires-Dist: click>=8.1.0
Requires-Dist: macholib>=1.15; platform_system == 'Darwin'
Requires-Dist: pefile>=2023.2.7; platform_system == 'Windows'
Requires-Dist: pydantic>=2.5.0
Requires-Dist: pyelftools>=0.27; platform_system == 'Linux'
Provides-Extra: dev
Requires-Dist: pytest; extra == 'dev'
